[
  {
    "Id": "408372",
    "ThreadId": "199649",
    "Html": "<p>hi, again!</p>\r\n<p>if i want another marker(like blue_dot, orange_dot) what should i do?(in WM)</p>\r\n<p>- jibin</p>",
    "PostedDate": "2010-02-26T05:28:34.467-08:00",
    "UserRole": null,
    "MarkedAsAnswerDate": null
  },
  {
    "Id": "408676",
    "ThreadId": "199649",
    "Html": "<p><a href=\"http://greatmaps.codeplex.com/wikipage?title=custom marker&referringTitle=GMap.NET.WindowsForms\">http://greatmaps.codeplex.com/wikipage?title=custom%20marker&amp;referringTitle=GMap.NET.WindowsForms</a></p>",
    "PostedDate": "2010-02-26T07:33:17.493-08:00",
    "UserRole": null,
    "MarkedAsAnswerDate": null
  },
  {
    "Id": "410415",
    "ThreadId": "199649",
    "Html": "<p>thanks i made it =}</p>",
    "PostedDate": "2010-02-26T18:37:09.363-08:00",
    "UserRole": null,
    "MarkedAsAnswerDate": null
  }
]