[
  {
    "Id": "442006",
    "ThreadId": "212410",
    "Html": "<p>I went through the forum, but no answer wasn't found(I can read...I think so)). Does route should work in offline mode? When I connected to Internet - it works, even if I choose CacheMode, but when cable disconnected, any my attempt to add route fails.</p>",
    "PostedDate": "2010-05-12T05:34:25.667-07:00",
    "UserRole": null,
    "MarkedAsAnswerDate": null
  },
  {
    "Id": "442015",
    "ThreadId": "212410",
    "Html": "<p>only cached routes works ;}</p>",
    "PostedDate": "2010-05-12T05:58:14.727-07:00",
    "UserRole": null,
    "MarkedAsAnswerDate": null
  }
]