[
  {
    "Id": "989553",
    "ThreadId": "430256",
    "Html": "\r\n<p>is the latest version for&nbsp;GMap.NET.WindowsMobile.dll is 1.4.9.3 or is there a new one?</p>\r\n",
    "PostedDate": "2013-01-21T00:46:53.73-08:00",
    "UserRole": null,
    "MarkedAsAnswerDate": null
  },
  {
    "Id": "989584",
    "ThreadId": "430256",
    "Html": "\r\n<p>there is no prebuild mobile dll, you have to build it yourself, just pick latest changeset and try build, if it doesn't work and you can't fix it, use latest changeset with a\r\n<span>phrase </span>'GMap.NET.WindowsMobile: sync'</p>\r\n",
    "PostedDate": "2013-01-21T01:57:18.753-08:00",
    "UserRole": null,
    "MarkedAsAnswerDate": null
  },
  {
    "Id": "989598",
    "ThreadId": "430256",
    "Html": "\r\n<p>how can i get the&nbsp;<span>latest changeset?</span></p>\r\n",
    "PostedDate": "2013-01-21T02:33:59.597-08:00",
    "UserRole": null,
    "MarkedAsAnswerDate": null
  }
]